BFPCode/BF.py
BFPCode/__init__.py
BFPCode/__main__.py
BFPCode-1.6.2.dist-info/LICENSE
BFPCode-1.6.2.dist-info/METADATA
BFPCode-1.6.2.dist-info/WHEEL
BFPCode-1.6.2.dist-info/top_level.txt
BFPCode-1.6.2.dist-info/RECORD
